ai_team_core_utils/__init__.py
ai_team_core_utils/base_model.py
ai_team_core_utils/base_repository.py
ai_team_core_utils/base_service.py
ai_team_core_utils/cache.py
ai_team_core_utils/database.py
ai_team_core_utils/dependencies.py
ai_team_core_utils/enums.py
ai_team_core_utils/exceptions.py
ai_team_core_utils/security.py
ai_team_core_utils/validators.py
ai_team_core_utils-0.1.0.dist-info/METADATA
ai_team_core_utils-0.1.0.dist-info/WHEEL
ai_team_core_utils-0.1.0.dist-info/RECORD
