Metadata-Version: 2.4
Name: ai-team-core-utils
Version: 0.1.0
Summary: AI Team Platform Core Utilities
Project-URL: Homepage, https://github.com/yourusername/ai-team-core-utils
Author: AI Team Platform Team
Classifier: License :: OSI Approved :: MIT License
Classifier: Operating System :: OS Independent
Classifier: Programming Language :: Python :: 3
Requires-Python: >=3.9
Requires-Dist: asyncpg>=0.29.0
Requires-Dist: bcrypt>=4.0.1
Requires-Dist: email-validator>=2.1.0.post1
Requires-Dist: fastapi>=0.109.0
Requires-Dist: passlib[bcrypt]>=1.7.4
Requires-Dist: pydantic>=2.5.3
Requires-Dist: python-jose[cryptography]>=3.3.0
Requires-Dist: python-multipart>=0.0.7
Requires-Dist: python-ulid>=2.2.0
Requires-Dist: redis>=5.0.1
Requires-Dist: sqlalchemy[asyncio]>=2.0.25
Requires-Dist: structlog>=24.1.0
